{
  "$schema": "https://developer.microsoft.com/json-schemas/fabric/item/report/definition/visualContainer/2.3.0/schema.json",
  "name": "8267eaa3cadfbe862a6e",
  "position": {
    "x": 16.457142857142859,
    "y": 19.2,
    "z": 8000,
    "height": 93.257142857142867,
    "width": 478.62857142857143,
    "tabOrder": 7000
  },
  "visual": {
    "visualType": "card",
    "query": {
      "queryState": {
        "Values": {
          "projections": [
            {
              "field": {
                "Aggregation": {
                  "Expression": {
                    "Column": {
                      "Expression": {
                        "SourceRef": {
                          "Entity": "d_gl_project"
                        }
                      },
                      "Property": "prj_code"
                    }
                  },
                  "Function": 3
                }
              },
              "queryRef": "Min(d_gl_project.prj_code)",
              "nativeQueryRef": "prj_code"
            }
          ]
        }
      }
    },
    "drillFilterOtherVisuals": true
  }
}