{
  "$schema": "https://developer.microsoft.com/json-schemas/fabric/item/report/definition/visualContainer/2.7.0/schema.json",
  "name": "aa37f1c2a0466d097219",
  "position": {
    "x": 0,
    "y": 46.995073891625616,
    "z": 2000,
    "height": 123.25123152709359,
    "width": 230.54187192118226,
    "tabOrder": 2000
  },
  "visual": {
    "visualType": "slicer",
    "query": {
      "queryState": {
        "Values": {
          "projections": [
            {
              "field": {
                "Column": {
                  "Expression": {
                    "SourceRef": {
                      "Entity": "Organization"
                    }
                  },
                  "Property": "Department"
                }
              },
              "queryRef": "Organization.Department",
              "nativeQueryRef": "Dział",
              "active": true
            }
          ]
        }
      }
    },
    "objects": {
      "data": [
        {
          "properties": {
            "mode": {
              "expr": {
                "Literal": {
                  "Value": "'Basic'"
                }
              }
            }
          }
        }
      ],
      "general": [
        {
          "properties": {
            "outlineWeight": {
              "expr": {
                "Literal": {
                  "Value": "1D"
                }
              }
            },
            "orientation": {
              "expr": {
                "Literal": {
                  "Value": "0D"
                }
              }
            }
          }
        }
      ],
      "header": [
        {
          "properties": {
            "textSize": {
              "expr": {
                "Literal": {
                  "Value": "12D"
                }
              }
            },
            "show": {
              "expr": {
                "Literal": {
                  "Value": "true"
                }
              }
            }
          }
        }
      ],
      "items": [
        {
          "properties": {
            "textSize": {
              "expr": {
                "Literal": {
                  "Value": "10D"
                }
              }
            },
            "padding": {
              "expr": {
                "Literal": {
                  "Value": "1D"
                }
              }
            },
            "outlineStyle": {
              "expr": {
                "Literal": {
                  "Value": "0D"
                }
              }
            }
          }
        }
      ]
    },
    "syncGroup": {
      "groupName": "Dział",
      "fieldChanges": true,
      "filterChanges": true
    },
    "drillFilterOtherVisuals": true
  },
  "filterConfig": {
    "filters": [
      {
        "name": "Filterbe12dea9eb9d373f07ec",
        "field": {
          "Column": {
            "Expression": {
              "SourceRef": {
                "Entity": "Organization"
              }
            },
            "Property": "Department"
          }
        },
        "type": "Categorical",
        "filter": {
          "Version": 2,
          "From": [
            {
              "Name": "o",
              "Entity": "Organization",
              "Type": 0
            }
          ],
          "Where": [
            {
              "Condition": {
                "In": {
                  "Expressions": [
                    {
                      "Column": {
                        "Expression": {
                          "SourceRef": {
                            "Source": "o"
                          }
                        },
                        "Property": "Department"
                      }
                    }
                  ],
                  "Values": [
                    [
                      {
                        "Literal": {
                          "Value": "'Dział Techniki'"
                        }
                      }
                    ],
                    [
                      {
                        "Literal": {
                          "Value": "'Fabryka Mebli Biurowych'"
                        }
                      }
                    ],
                    [
                      {
                        "Literal": {
                          "Value": "'Zakład Produkcji Foteli i Krzeseł'"
                        }
                      }
                    ],
                    [
                      {
                        "Literal": {
                          "Value": "'Zakład Produkcji Metalowej'"
                        }
                      }
                    ],
                    [
                      {
                        "Literal": {
                          "Value": "'Zakład Montażowy Warzyce'"
                        }
                      }
                    ],
                    [
                      {
                        "Literal": {
                          "Value": "'Zakład Produkcji Drzewnej'"
                        }
                      }
                    ],
                    [
                      {
                        "Literal": {
                          "Value": "'Zakład Przemysłu Drzewnego'"
                        }
                      }
                    ]
                  ]
                }
              }
            }
          ]
        }
      }
    ]
  }
}