{
  "$schema": "https://developer.microsoft.com/json-schemas/fabric/item/report/definition/visualContainer/2.10.0/schema.json",
  "name": "e6719fee0340e7415347",
  "position": {
    "x": 0,
    "y": 51.478328325508187,
    "z": 2000,
    "height": 180.16366612111293,
    "width": 1069.4599018003273,
    "tabOrder": 2000
  },
  "visual": {
    "visualType": "lineChart",
    "query": {
      "queryState": {
        "Category": {
          "projections": [
            {
              "field": {
                "Column": {
                  "Expression": {
                    "SourceRef": {
                      "Entity": "Date"
                    }
                  },
                  "Property": "Month Code"
                }
              },
              "queryRef": "Date.Month Code",
              "nativeQueryRef": "Month Code",
              "active": true
            }
          ]
        },
        "Y": {
          "projections": [
            {
              "field": {
                "Measure": {
                  "Expression": {
                    "SourceRef": {
                      "Entity": "Salary Costs Measures"
                    }
                  },
                  "Property": "Produktywność BP 1"
                }
              },
              "queryRef": "Salary Costs Measures.Produktywność BP 1",
              "nativeQueryRef": "Produktywność BP 11"
            },
            {
              "field": {
                "Measure": {
                  "Expression": {
                    "SourceRef": {
                      "Entity": "Salary Costs Measures"
                    }
                  },
                  "Property": "Produktywność BP 2"
                }
              },
              "queryRef": "Salary Costs Measures.Produktywność BP 2",
              "nativeQueryRef": "Produktywność BP 2"
            }
          ]
        }
      },
      "sortDefinition": {
        "sort": [
          {
            "field": {
              "Column": {
                "Expression": {
                  "SourceRef": {
                    "Entity": "Date"
                  }
                },
                "Property": "Month Code"
              }
            },
            "direction": "Ascending"
          }
        ]
      }
    },
    "objects": {
      "valueAxis": [
        {
          "properties": {
            "fontSize": {
              "expr": {
                "Literal": {
                  "Value": "8D"
                }
              }
            },
            "showAxisTitle": {
              "expr": {
                "Literal": {
                  "Value": "false"
                }
              }
            }
          }
        }
      ],
      "categoryAxis": [
        {
          "properties": {
            "fontSize": {
              "expr": {
                "Literal": {
                  "Value": "8D"
                }
              }
            },
            "showAxisTitle": {
              "expr": {
                "Literal": {
                  "Value": "false"
                }
              }
            }
          }
        }
      ]
    },
    "visualContainerObjects": {
      "title": [
        {
          "properties": {
            "show": {
              "expr": {
                "Literal": {
                  "Value": "false"
                }
              }
            },
            "titleWrap": {
              "expr": {
                "Literal": {
                  "Value": "true"
                }
              }
            },
            "fontColor": {
              "solid": {
                "color": {
                  "expr": {
                    "Literal": {
                      "Value": "'#252525'"
                    }
                  }
                }
              }
            }
          }
        }
      ],
      "background": [
        {
          "properties": {
            "show": {
              "expr": {
                "Literal": {
                  "Value": "true"
                }
              }
            },
            "transparency": {
              "expr": {
                "Literal": {
                  "Value": "0D"
                }
              }
            }
          }
        }
      ],
      "border": [
        {
          "properties": {
            "width": {
              "expr": {
                "Literal": {
                  "Value": "1D"
                }
              }
            }
          }
        }
      ]
    },
    "drillFilterOtherVisuals": true
  },
  "parentGroupName": "1ac2fdd4dadcc2193e97"
}