{
  "$schema": "https://developer.microsoft.com/json-schemas/fabric/item/report/definition/visualContainer/2.10.0/schema.json",
  "name": "0106cc12025a0d4aa88d",
  "position": {
    "x": 0,
    "y": 284.77611940298505,
    "z": 14000,
    "height": 40.298507462686565,
    "width": 46.567164179104473,
    "tabOrder": 14000
  },
  "visual": {
    "visualType": "actionButton",
    "objects": {
      "icon": [
        {
          "properties": {
            "shapeType": {
              "expr": {
                "Literal": {
                  "Value": "'information'"
                }
              }
            }
          },
          "selector": {
            "id": "default"
          }
        }
      ]
    },
    "drillFilterOtherVisuals": true
  },
  "howCreated": "InsertVisualButton"
}