{
  "$schema": "https://developer.microsoft.com/json-schemas/fabric/item/report/definition/visualContainer/2.7.0/schema.json",
  "name": "3fbd8134048d0c094e17",
  "position": {
    "x": 98.75,
    "y": 126.25,
    "z": 4000,
    "height": 45,
    "width": 145,
    "tabOrder": 4000
  },
  "visual": {
    "visualType": "slicer",
    "query": {
      "queryState": {
        "Values": {
          "projections": [
            {
              "field": {
                "Column": {
                  "Expression": {
                    "SourceRef": {
                      "Entity": "Ledger Ind"
                    }
                  },
                  "Property": "Ledg"
                }
              },
              "queryRef": "Ledger Ind.Ledg",
              "nativeQueryRef": "Wskaźnik",
              "active": true
            }
          ]
        }
      },
      "sortDefinition": {
        "sort": [
          {
            "field": {
              "Column": {
                "Expression": {
                  "SourceRef": {
                    "Entity": "Ledger Ind"
                  }
                },
                "Property": "Ledg"
              }
            },
            "direction": "Ascending"
          }
        ]
      }
    },
    "objects": {
      "data": [
        {
          "properties": {
            "mode": {
              "expr": {
                "Literal": {
                  "Value": "'Basic'"
                }
              }
            }
          }
        }
      ],
      "general": [
        {
          "properties": {}
        }
      ],
      "items": [
        {
          "properties": {
            "textSize": {
              "expr": {
                "Literal": {
                  "Value": "10D"
                }
              }
            },
            "padding": {
              "expr": {
                "Literal": {
                  "Value": "0D"
                }
              }
            }
          }
        }
      ],
      "header": [
        {
          "properties": {
            "show": {
              "expr": {
                "Literal": {
                  "Value": "false"
                }
              }
            }
          }
        }
      ]
    },
    "syncGroup": {
      "groupName": "Wskaźnik",
      "fieldChanges": true,
      "filterChanges": true
    },
    "drillFilterOtherVisuals": true
  },
  "filterConfig": {
    "filters": [
      {
        "name": "Filter6d261caf0228f9e2fb4f",
        "field": {
          "Column": {
            "Expression": {
              "SourceRef": {
                "Entity": "Ledger Ind"
              }
            },
            "Property": "Ledg"
          }
        },
        "type": "Categorical",
        "filter": {
          "Version": 2,
          "From": [
            {
              "Name": "l",
              "Entity": "Ledger Ind",
              "Type": 0
            }
          ],
          "Where": [
            {
              "Condition": {
                "In": {
                  "Expressions": [
                    {
                      "Column": {
                        "Expression": {
                          "SourceRef": {
                            "Source": "l"
                          }
                        },
                        "Property": "Ledg"
                      }
                    }
                  ],
                  "Values": [
                    [
                      {
                        "Literal": {
                          "Value": "'Wyksiegowane'"
                        }
                      }
                    ],
                    [
                      {
                        "Literal": {
                          "Value": "'Zaksiegowane'"
                        }
                      }
                    ]
                  ]
                }
              }
            }
          ]
        },
        "objects": {
          "general": [
            {
              "properties": {}
            }
          ]
        }
      }
    ]
  }
}